{"stat.walkOneCm":401941,"stat.pickup.minecraft.gold_ore":1,"stat.leaveGame":4,"stat.flyOneCm":155623,"stat.pickup.minecraft.wheat_seeds":16,"stat.jump":463,"stat.swimOneCm":14822,"stat.playOneMinute":118018,"stat.sneakTime":157,"stat.pickup.quark.tallow":2,"stat.pickup.minecraft.porkchop":1,"stat.crouchOneCm":4,"stat.timeSinceDeath":118018,"stat.pickup.minecraft.sapling":652,"stat.pickup.minecraft.yellow_flower":1,"stat.sprintOneCm":1682,"stat.useItem.minecraft.stone_slab2":139,"stat.pickup.minecraft.apple":1,"stat.diveOneCm":4362}